{
  "kind": "collectionType",
  "collectionName": "projects",
  "info": {
    "singularName": "project",
    "pluralName": "projects",
    "displayName": "Project"
  },
  "options": {
    "draftAndPublish": true
  },
  "pluginOptions": {
    "i18n": {
      "localized": true
    }
  },
  "attributes": {
    "name": {
      "pluginOptions": {
        "i18n": {
          "localized": true
        }
      },
      "type": "string",
      "required": true,
      "maxLength": 128,
      "minLength": 5,
      "unique": false
    },
    "status": {
      "pluginOptions": {
        "i18n": {
          "localized": true
        }
      },
      "type": "enumeration",
      "enum": [
        "Pending",
        "Active",
        "Complete"
      ]
    },
    "guilds_involved": {
      "pluginOptions": {
        "i18n": {
          "localized": true
        }
      },
      "type": "json",
      "required": true
    },
    "contributors": {
      "pluginOptions": {
        "i18n": {
          "localized": true
        }
      },
      "type": "json",
      "required": true
    },
    "notes": {
      "pluginOptions": {
        "i18n": {
          "localized": true
        }
      },
      "type": "richtext"
    }
  }
}
